{
    "resourceType": "Patient",
    "id": "CC1234567890",
    "meta": {
        "versionId": "1",
        "lastUpdated": "2024-11-25T17:53:52.340-06:00",
        "source": "#UhdTmTa8SEboFDE7"
    },
    "name": [
        {
            "use": "official",
            "family": "CORAL REVELO",
            "given": [
                "JHON HENRY"
            ]
        }
    ],
    "telecom": [
        {
            "system": "phone",
            "value": "3123456789",
            "use": "mobile"
        },
        {
            "system": "email",
            "value": "jhoncoralm@gmail.com"
        }
    ],
    "address": [
        {
            "use": "home",
            "line": [
                "BARRIO LOS ALAMOS"
            ]
        }
    ]
}